nexom/__init__.py
nexom/__main__.py
nexom/app/__init__.py
nexom/app/auth.py
nexom/app/cookie.py
nexom/app/db.py
nexom/app/http_status_codes.py
nexom/app/middleware.py
nexom/app/path.py
nexom/app/request.py
nexom/app/response.py
nexom/app/template.py
nexom/app/user.py
nexom/assets/app/__init__.py
nexom/assets/app/config.py
nexom/assets/app/gunicorn.conf.py
nexom/assets/app/router.py
nexom/assets/app/wsgi.py
nexom/assets/app/__pycache__/__init__.cpython-313.pyc
nexom/assets/app/pages/__init__.py
nexom/assets/app/pages/_templates.py
nexom/assets/app/pages/default.py
nexom/assets/app/pages/document.py
nexom/assets/app/pages/__pycache__/__init__.cpython-313.pyc
nexom/assets/app/static/dog.jpeg
nexom/assets/app/static/github.png
nexom/assets/app/static/style.css
nexom/assets/app/templates/base.html
nexom/assets/app/templates/default.html
nexom/assets/app/templates/document.html
nexom/assets/app/templates/footer.html
nexom/assets/app/templates/header.html
nexom/assets/auth/__init__.py
nexom/assets/auth/config.py
nexom/assets/auth/gunicorn.conf.py
nexom/assets/auth/wsgi.py
nexom/assets/auth/__pycache__/__init__.cpython-313.pyc
nexom/assets/auth_page/login.html
nexom/assets/auth_page/signup.html
nexom/assets/error_page/error.html
nexom/assets/gateway/apache_app.conf
nexom/assets/gateway/nginx_app.conf
nexom/buildTools/__init__.py
nexom/buildTools/build.py
nexom/buildTools/run.py
nexom/core/__init__.py
nexom/core/error.py
nexom/core/log.py
nexom/core/object_html_render.py
nexom/templates/__init__.py
nexom/templates/auth.py
nexom-1.0.9.dist-info/licenses/LICENSE
nexom-1.0.9.dist-info/METADATA
nexom-1.0.9.dist-info/WHEEL
nexom-1.0.9.dist-info/entry_points.txt
nexom-1.0.9.dist-info/top_level.txt
nexom-1.0.9.dist-info/RECORD
