Metadata-Version: 2.4
Name: Nexom
Version: 1.0.9
Summary: Lightweight Python Web Framework (WSGI)
Author: TouriAida
License: MIT License
Project-URL: Homepage, https://nexom.ceez7.com
Project-URL: Repository, https://github.com/ait913/Nexom
Project-URL: Issues, https://github.com/ait913/Nexom/issues
Keywords: wsgi,web,framework
Requires-Python: >=3.10
License-File: LICENSE
Requires-Dist: gunicorn>=21.2
Dynamic: license-file
